{"cameraMode":{"drawMode":0,"name":"Shaded","section":"Shading Mode"},"sceneLighting":true,"audioPlay":false,"sceneViewState":{"m_AlwaysRefresh":false,"showFog":true,"showSkybox":true,"showFlares":true,"showImageEffects":true,"showParticleSystems":true,"showVisualEffectGraphs":true,"m_FxEnabled":true},"in2DMode":false,"pivot":{"x":303.1943664550781,"y":61.730472564697269,"z":-787.6705322265625},"rotation":{"x":0.030782856047153474,"y":-0.7589386701583862,"z":-0.03563666716217995,"w":-0.649678647518158},"size":0.6449540853500366,"orthographic":false}